MANIFEST.in
README.rst
setup.py
eoffcn_ai/__init__.py
eoffcn_ai/explain.py
eoffcn_ai.egg-info/PKG-INFO
eoffcn_ai.egg-info/SOURCES.txt
eoffcn_ai.egg-info/dependency_links.txt
eoffcn_ai.egg-info/requires.txt
eoffcn_ai.egg-info/top_level.txt
eoffcn_ai/image/__init__.py
eoffcn_ai/image/process.py
eoffcn_ai/image/tool.py
eoffcn_ai/image/qrdecode/__init__.py
eoffcn_ai/image/qrdecode/ZBar_Win/zbarvars.bat
eoffcn_ai/image/qrdecode/ZBar_Win/bin/libMagickCore-2.dll
eoffcn_ai/image/qrdecode/ZBar_Win/bin/libMagickWand-2.dll
eoffcn_ai/image/qrdecode/ZBar_Win/bin/libiconv-2.dll
eoffcn_ai/image/qrdecode/ZBar_Win/bin/libjpeg-7.dll
eoffcn_ai/image/qrdecode/ZBar_Win/bin/libpng12-0.dll
eoffcn_ai/image/qrdecode/ZBar_Win/bin/libtiff-3.dll
eoffcn_ai/image/qrdecode/ZBar_Win/bin/libxml2-2.dll
eoffcn_ai/image/qrdecode/ZBar_Win/bin/libzbar-0.dll
eoffcn_ai/image/qrdecode/ZBar_Win/bin/zbarcam.bat
eoffcn_ai/image/qrdecode/ZBar_Win/bin/zbarcam.exe
eoffcn_ai/image/qrdecode/ZBar_Win/bin/zbarimg.exe
eoffcn_ai/image/qrdecode/ZBar_Win/bin/zlib1.dll
eoffcn_ai/image/qrdecode/php_qrdecode/composer.json
eoffcn_ai/image/qrdecode/php_qrdecode/decode.php
eoffcn_ai/image/qrdecode/php_qrdecode/vendor/autoload.php
eoffcn_ai/image/qrdecode/php_qrdecode/vendor/composer/ClassLoader.php
eoffcn_ai/image/qrdecode/php_qrdecode/vendor/composer/LICENSE
eoffcn_ai/image/qrdecode/php_qrdecode/vendor/composer/autoload_classmap.php
eoffcn_ai/image/qrdecode/php_qrdecode/vendor/composer/autoload_files.php
eoffcn_ai/image/qrdecode/php_qrdecode/vendor/composer/autoload_namespaces.php
eoffcn_ai/image/qrdecode/php_qrdecode/vendor/composer/autoload_psr4.php
eoffcn_ai/image/qrdecode/php_qrdecode/vendor/composer/autoload_real.php
eoffcn_ai/image/qrdecode/php_qrdecode/vendor/composer/autoload_static.php
eoffcn_ai/image/qrdecode/php_qrdecode/vendor/composer/installed.json
eoffcn_ai/image/qrdecode/php_qrdecode/vendor/khanamiryan/qrcode-detector-decoder/.gitignore
eoffcn_ai/image/qrdecode/php_qrdecode/vendor/khanamiryan/qrcode-detector-decoder/README.md
eoffcn_ai/image/qrdecode/php_qrdecode/vendor/khanamiryan/qrcode-detector-decoder/composer.json
