Metadata-Version: 1.0
Name: eoffcn-ai
Version: 0.1.6
Summary: eoffcn ai api.
Home-page: UNKNOWN
Author: PuKun
Author-email: pukun@offcn.com
License: UNKNOWN
Platform: any
